LICENSE
MANIFEST.in
README.md
setup.cfg
setup.py
bin/cdhistory
cdhistory/__init__.py
cdhistory/history.py
cdhistory.egg-info/PKG-INFO
cdhistory.egg-info/SOURCES.txt
cdhistory.egg-info/dependency_links.txt
cdhistory.egg-info/requires.txt
cdhistory.egg-info/top_level.txt
share/cdhistory.bash