Metadata-Version: 1.1
Name: cdhistory
Version: 0.1
Summary: Search for frequently visited directories
Home-page: http://github.com/jdowner/cdhistory
Author: Joshua Downer
Author-email: joshua.downer@gmail.com
License: MIT
Keywords: cd directory history alias search
Platform: Unix
Classifier: Development Status :: 4 - Beta
Classifier: Environment :: Console
Classifier: Intended Audience :: Developers
Classifier: Intended Audience :: System Administrators
Classifier: License :: OSI Approved :: MIT License
Classifier: Operating System :: Unix
Classifier: Programming Language :: Python
Classifier: Programming Language :: Python :: 2
Classifier: Programming Language :: Python :: 2.7
Classifier: Programming Language :: Python :: 3
Classifier: Programming Language :: Python :: 3.3
Classifier: Programming Language :: Python :: 3.4
Classifier: Topic :: Utilities
